{
  "id": "monaco-11b91654-102f-30cc-8a77-9ac17db03c87",
  "name": "[SRE] Azure storage accounts for isolate data",
  "type": "dashboard",
  "version": 2339,
  "owner": "c3358523-17c3-4270-994c-09c45bfa97d6",
  "isPrivate": false,
  "modificationInfo": {
    "createdBy": "c3358523-17c3-4270-994c-09c45bfa97d6",
    "createdTime": "2025-05-13T11:35:58.449Z",
    "lastModifiedBy": "c3358523-17c3-4270-994c-09c45bfa97d6",
    "lastModifiedTime": "2026-04-10T15:09:07.782Z"
  },
  "access": [
    "read"
  ]
}
