{
  "id": "monaco-58938c5e-f6ca-382a-b1d8-2036d49ef1e0",
  "name": "[TSG] FDI - Classic Problem Notification Service",
  "type": "dashboard",
  "version": 639,
  "owner": "c3358523-17c3-4270-994c-09c45bfa97d6",
  "isPrivate": false,
  "modificationInfo": {
    "createdBy": "c3358523-17c3-4270-994c-09c45bfa97d6",
    "createdTime": "2024-12-10T02:41:57.624Z",
    "lastModifiedBy": "c3358523-17c3-4270-994c-09c45bfa97d6",
    "lastModifiedTime": "2026-04-10T14:54:52.964Z"
  },
  "access": [
    "read"
  ]
}
